geoserver/__init__.py
geoserver/catalog.py
geoserver/layer.py
geoserver/layergroup.py
geoserver/resource.py
geoserver/settings.py
geoserver/store.py
geoserver/style.py
geoserver/support.py
geoserver/util.py
geoserver/workspace.py
gsconfig_py3-1.0.8.dist-info/METADATA
gsconfig_py3-1.0.8.dist-info/WHEEL
gsconfig_py3-1.0.8.dist-info/top_level.txt
gsconfig_py3-1.0.8.dist-info/RECORD
