Metadata-Version: 1.2
Name: gsconfig-py3
Version: 1.0.8
Summary: GeoServer REST Configuration
Home-page: https://github.com/quadratic-be/gsconfig-py3
Author: Dimitri Justeau (IAC/AMAP)
Author-email: dimitri.justeau@gmail.com
Maintainer: Renato Primavera (Quadratic)
Maintainer-email: renato.primavera@quadratic.be
License: UNKNOWN
Platform: UNKNOWN
Classifier: Development Status :: 4 - Beta
Classifier: Intended Audience :: Developers
Classifier: Intended Audience :: Science/Research
Classifier: License :: OSI Approved :: MIT License
Classifier: Operating System :: OS Independent
Classifier: Programming Language :: Python :: 3
Classifier: Topic :: Scientific/Engineering :: GIS
